tailon/__init__.py
tailon/__main__.py
tailon/argparse.py
tailon/commands.py
tailon/compat.py
tailon/main.py
tailon/server.py
tailon/utils.py
tailon/assets/fonts/.keep
tailon/assets/fonts/fontawesome-webfont.eot
tailon/assets/fonts/fontawesome-webfont.svg
tailon/assets/fonts/fontawesome-webfont.ttf
tailon/assets/fonts/fontawesome-webfont.woff
tailon/assets/fonts/fontawesome-webfont.woff2
tailon/assets/gen/.keep
tailon/assets/gen/3rdparty.css
tailon/assets/gen/3rdparty.js
tailon/assets/gen/Main.js
tailon/assets/gen/Main.js.map
tailon/assets/gen/Main.min.js
tailon/assets/gen/main.css
tailon/assets/gen/selectize.css
tailon/templates/base.html
tailon/templates/tailon.html
tailon-1.4.3.dist-info/METADATA
tailon-1.4.3.dist-info/RECORD
tailon-1.4.3.dist-info/WHEEL
tailon-1.4.3.dist-info/entry_points.txt
tailon-1.4.3.dist-info/top_level.txt
