Metadata-Version: 2.1
Name: tailon
Version: 1.4.3
Summary: Webapp for looking at and searching through log files
Home-page: https://github.com/gvalkov/tailon-legacy
Author: Georgi Valkov
Author-email: georgi.t.valkov@gmail.com
License: Revised BSD License
Keywords: log monitoring tail
Platform: UNKNOWN
Classifier: Development Status :: 5 - Production/Stable
Classifier: Programming Language :: Python :: 2.7
Classifier: Programming Language :: Python :: 3
Classifier: License :: OSI Approved :: BSD License
Classifier: Intended Audience :: Developers
Requires-Dist: deepmerge
Requires-Dist: tornado (<5.0.0,>=4.0.0)
Requires-Dist: tornado-http-auth (>=1.0.0)
Requires-Dist: sockjs-tornado (>=1.0.0)
Requires-Dist: PyYAML (>=3.11)
